nion/nionswift_tool/__init__.py
nion/nionswift_tool/command.py
nionswift_tool-5.1.5.data/data/bin/Nion Swift.app.tar.gz
nionswift_tool-5.1.5.data/data/bin/Nion Swift.app/Contents/Info.plist
nionswift_tool-5.1.5.data/data/bin/Nion Swift.app/Contents/Frameworks/QtCore.framework/Versions/A/QtCore
nionswift_tool-5.1.5.data/data/bin/Nion Swift.app/Contents/Frameworks/QtCore.framework/Versions/A/Resources/Info.plist
nionswift_tool-5.1.5.data/data/bin/Nion Swift.app/Contents/Frameworks/QtCore.framework/Versions/A/Resources/PrivacyInfo.xcprivacy
nionswift_tool-5.1.5.data/data/bin/Nion Swift.app/Contents/Frameworks/QtCore.framework/Versions/A/_CodeSignature/CodeResources
nionswift_tool-5.1.5.data/data/bin/Nion Swift.app/Contents/Frameworks/QtDBus.framework/Versions/A/QtDBus
nionswift_tool-5.1.5.data/data/bin/Nion Swift.app/Contents/Frameworks/QtDBus.framework/Versions/A/Resources/Info.plist
nionswift_tool-5.1.5.data/data/bin/Nion Swift.app/Contents/Frameworks/QtDBus.framework/Versions/A/Resources/PrivacyInfo.xcprivacy
nionswift_tool-5.1.5.data/data/bin/Nion Swift.app/Contents/Frameworks/QtDBus.framework/Versions/A/_CodeSignature/CodeResources
nionswift_tool-5.1.5.data/data/bin/Nion Swift.app/Contents/Frameworks/QtGui.framework/Versions/A/QtGui
nionswift_tool-5.1.5.data/data/bin/Nion Swift.app/Contents/Frameworks/QtGui.framework/Versions/A/Resources/Info.plist
nionswift_tool-5.1.5.data/data/bin/Nion Swift.app/Contents/Frameworks/QtGui.framework/Versions/A/Resources/PrivacyInfo.xcprivacy
nionswift_tool-5.1.5.data/data/bin/Nion Swift.app/Contents/Frameworks/QtGui.framework/Versions/A/_CodeSignature/CodeResources
nionswift_tool-5.1.5.data/data/bin/Nion Swift.app/Contents/Frameworks/QtSvg.framework/Versions/A/QtSvg
nionswift_tool-5.1.5.data/data/bin/Nion Swift.app/Contents/Frameworks/QtSvg.framework/Versions/A/Resources/Info.plist
nionswift_tool-5.1.5.data/data/bin/Nion Swift.app/Contents/Frameworks/QtSvg.framework/Versions/A/Resources/PrivacyInfo.xcprivacy
nionswift_tool-5.1.5.dist-info/licenses/LICENSE
nionswift_tool-5.1.5.dist-info/licenses/NOTICES
nionswift_tool-5.1.5.dist-info/METADATA
nionswift_tool-5.1.5.dist-info/WHEEL
nionswift_tool-5.1.5.dist-info/entry_points.txt
nionswift_tool-5.1.5.dist-info/top_level.txt
nionswift_tool-5.1.5.dist-info/RECORD
