Metadata-Version: 2.4
Name: nionswift-tool
Version: 5.1.5
Summary: Python command line access to Nion Swift Launcher
Home-page: https://github.com/nion-software/nionswift-tool
Author: Nion Software Team
Author-email: software@nion.com
License: Apache-2.0
Classifier: License :: OSI Approved :: Apache Software License
License-File: LICENSE
License-File: NOTICES
Requires-Dist: numpy<3.0,>=2.0
Dynamic: author
Dynamic: author-email
Dynamic: classifier
Dynamic: description
Dynamic: home-page
Dynamic: license
Dynamic: license-file
Dynamic: requires-dist
Dynamic: summary
